CellLayers/CellLayers.py
CellLayers/CoExpressionSankey.py
CellLayers/EnrichmentAnalysis.py
CellLayers/EnrichmentSankey.py
CellLayers/MultiResolutionAnalysis.py
CellLayers/Sankey.py
CellLayers/__init__.py
CellLayers/.ipynb_checkpoints/CellLayers-checkpoint.py
CellLayers/.ipynb_checkpoints/CoExpressionSankey-checkpoint.py
CellLayers/.ipynb_checkpoints/EnrichmentAnalysis-checkpoint.py
CellLayers/.ipynb_checkpoints/EnrichmentSankey-checkpoint.py
CellLayers/.ipynb_checkpoints/MultiResolutionAnalysis-checkpoint.py
CellLayers/.ipynb_checkpoints/Sankey-checkpoint.py
celllayers-0.2.2.dist-info/LICENSE
celllayers-0.2.2.dist-info/WHEEL
celllayers-0.2.2.dist-info/METADATA
celllayers-0.2.2.dist-info/RECORD
