Metadata-Version: 2.1
Name: CellLayers
Version: 0.2.2
Summary: Cell Layers
Author-email: Andrew Blair <andrew.blair@ucsf.edu>
Classifier: License :: OSI Approved :: MIT License
Requires-Dist: matplotlib==3.5.1
Requires-Dist: numpy==1.21.2
Requires-Dist: pandas==1.4.1
Requires-Dist: plotly==5.7.0
Requires-Dist: chart-studio==1.1.0
Requires-Dist: scipy==1.7.3
Requires-Dist: nbsphinx
Requires-Dist: pytest
Project-URL: Home, https://github.com/apblair/CellLayers
